Pre_processor/__init__.py
Pre_processor/preprocessor.py
Pre_processor-0.0.7.dist-info/LICENSE.txt
Pre_processor-0.0.7.dist-info/METADATA
Pre_processor-0.0.7.dist-info/WHEEL
Pre_processor-0.0.7.dist-info/top_level.txt
Pre_processor-0.0.7.dist-info/RECORD
