Metadata-Version: 2.1
Name: Pre-processor
Version: 0.0.7
Summary: csv and json file preprocessor
Home-page: https://github.com/ndevsinha/Pre_processor
Author: Neeraj Kumar
Author-email: neeraj_kumar22@optum.com
License: UNKNOWN
Download-URL: https://github.com/ndevsinha/Pre_processor/archive/0.0.7.tar.gz
Platform: UNKNOWN
Classifier: Programming Language :: Python :: 3
Classifier: License :: OSI Approved :: MIT License
Classifier: Operating System :: OS Independent
Requires-Python: >=3.6
